8c8
<        1: invokespecial #7                  // Method java/lang/Object."<init>":()V
---
>        1: invokespecial #2                  // Method java/lang/Object."<init>":()V
11c11
<        6: invokestatic  #12                 // Method com/squareup/okhttp/Headers$Builder.access$000:(Lcom/squareup/okhttp/Headers$Builder;)Ljava/util/List;
---
>        6: invokestatic  #3                  // Method com/squareup/okhttp/Headers$Builder.access$000:(Lcom/squareup/okhttp/Headers$Builder;)Ljava/util/List;
13,18c13,18
<       10: invokestatic  #12                 // Method com/squareup/okhttp/Headers$Builder.access$000:(Lcom/squareup/okhttp/Headers$Builder;)Ljava/util/List;
<       13: invokeinterface #18,  1           // InterfaceMethod java/util/List.size:()I
<       18: anewarray     #24                 // class java/lang/String
<       21: invokeinterface #26,  2           // InterfaceMethod java/util/List.toArray:([Ljava/lang/Object;)[Ljava/lang/Object;
<       26: checkcast     #30                 // class "[Ljava/lang/String;"
<       29: putfield      #32                 // Field namesAndValues:[Ljava/lang/String;
---
>       10: invokestatic  #3                  // Method com/squareup/okhttp/Headers$Builder.access$000:(Lcom/squareup/okhttp/Headers$Builder;)Ljava/util/List;
>       13: invokeinterface #4,  1            // InterfaceMethod java/util/List.size:()I
>       18: anewarray     #5                  // class java/lang/String
>       21: invokeinterface #6,  2            // InterfaceMethod java/util/List.toArray:([Ljava/lang/Object;)[Ljava/lang/Object;
>       26: checkcast     #7                  // class "[Ljava/lang/String;"
>       29: putfield      #8                  // Field namesAndValues:[Ljava/lang/String;
24c24
<        1: invokespecial #7                  // Method java/lang/Object."<init>":()V
---
>        1: invokespecial #2                  // Method java/lang/Object."<init>":()V
27c27
<        6: putfield      #32                 // Field namesAndValues:[Ljava/lang/String;
---
>        6: putfield      #8                  // Field namesAndValues:[Ljava/lang/String;
33c33
<        1: getfield      #32                 // Field namesAndValues:[Ljava/lang/String;
---
>        1: getfield      #8                  // Field namesAndValues:[Ljava/lang/String;
35c35
<        5: invokestatic  #35                 // Method get:([Ljava/lang/String;Ljava/lang/String;)Ljava/lang/String;
---
>        5: invokestatic  #9                  // Method get:([Ljava/lang/String;Ljava/lang/String;)Ljava/lang/String;
42c42
<        2: invokevirtual #39                 // Method get:(Ljava/lang/String;)Ljava/lang/String;
---
>        2: invokevirtual #10                 // Method get:(Ljava/lang/String;)Ljava/lang/String;
47c47
<       11: invokestatic  #42                 // Method com/squareup/okhttp/internal/http/HttpDate.parse:(Ljava/lang/String;)Ljava/util/Date;
---
>       11: invokestatic  #11                 // Method com/squareup/okhttp/internal/http/HttpDate.parse:(Ljava/lang/String;)Ljava/util/Date;
55c55
<        1: getfield      #32                 // Field namesAndValues:[Ljava/lang/String;
---
>        1: getfield      #8                  // Field namesAndValues:[Ljava/lang/String;
71c71
<       10: getfield      #32                 // Field namesAndValues:[Ljava/lang/String;
---
>       10: getfield      #8                  // Field namesAndValues:[Ljava/lang/String;
77c77
<       20: getfield      #32                 // Field namesAndValues:[Ljava/lang/String;
---
>       20: getfield      #8                  // Field namesAndValues:[Ljava/lang/String;
94c94
<       12: getfield      #32                 // Field namesAndValues:[Ljava/lang/String;
---
>       12: getfield      #8                  // Field namesAndValues:[Ljava/lang/String;
100c100
<       22: getfield      #32                 // Field namesAndValues:[Ljava/lang/String;
---
>       22: getfield      #8                  // Field namesAndValues:[Ljava/lang/String;
107c107
<        0: new           #48                 // class java/util/TreeSet
---
>        0: new           #12                 // class java/util/TreeSet
109,110c109,110
<        4: getstatic     #50                 // Field java/lang/String.CASE_INSENSITIVE_ORDER:Ljava/util/Comparator;
<        7: invokespecial #54                 // Method java/util/TreeSet."<init>":(Ljava/util/Comparator;)V
---
>        4: getstatic     #13                 // Field java/lang/String.CASE_INSENSITIVE_ORDER:Ljava/util/Comparator;
>        7: invokespecial #14                 // Method java/util/TreeSet."<init>":(Ljava/util/Comparator;)V
115c115
<       14: invokevirtual #57                 // Method size:()I
---
>       14: invokevirtual #15                 // Method size:()I
123,124c123,124
<       26: invokevirtual #58                 // Method name:(I)Ljava/lang/String;
<       29: invokevirtual #62                 // Method java/util/TreeSet.add:(Ljava/lang/Object;)Z
---
>       26: invokevirtual #16                 // Method name:(I)Ljava/lang/String;
>       29: invokevirtual #17                 // Method java/util/TreeSet.add:(Ljava/lang/Object;)Z
129c129
<       40: invokestatic  #66                 // Method java/util/Collections.unmodifiableSet:(Ljava/util/Set;)Ljava/util/Set;
---
>       40: invokestatic  #18                 // Method java/util/Collections.unmodifiableSet:(Ljava/util/Set;)Ljava/util/Set;
139c139
<        5: invokevirtual #57                 // Method size:()I
---
>        5: invokevirtual #15                 // Method size:()I
147,148c147,148
<       19: invokevirtual #58                 // Method name:(I)Ljava/lang/String;
<       22: invokevirtual #72                 // Method java/lang/String.equalsIgnoreCase:(Ljava/lang/String;)Z
---
>       19: invokevirtual #16                 // Method name:(I)Ljava/lang/String;
>       22: invokevirtual #19                 // Method java/lang/String.equalsIgnoreCase:(Ljava/lang/String;)Z
152c152
<       32: new           #76                 // class java/util/ArrayList
---
>       32: new           #20                 // class java/util/ArrayList
155c155
<       37: invokespecial #78                 // Method java/util/ArrayList."<init>":(I)V
---
>       37: invokespecial #21                 // Method java/util/ArrayList."<init>":(I)V
160,161c160,161
<       44: invokevirtual #81                 // Method value:(I)Ljava/lang/String;
<       47: invokeinterface #84,  2           // InterfaceMethod java/util/List.add:(Ljava/lang/Object;)Z
---
>       44: invokevirtual #22                 // Method value:(I)Ljava/lang/String;
>       47: invokeinterface #23,  2           // InterfaceMethod java/util/List.add:(Ljava/lang/Object;)Z
168c168
<       64: invokestatic  #85                 // Method java/util/Collections.unmodifiableList:(Ljava/util/List;)Ljava/util/List;
---
>       64: invokestatic  #24                 // Method java/util/Collections.unmodifiableList:(Ljava/util/List;)Ljava/util/List;
170c170
<       70: invokestatic  #89                 // Method java/util/Collections.emptyList:()Ljava/util/List;
---
>       70: invokestatic  #25                 // Method java/util/Collections.emptyList:()Ljava/util/List;
175c175
<        0: new           #13                 // class com/squareup/okhttp/Headers$Builder
---
>        0: new           #26                 // class com/squareup/okhttp/Headers$Builder
177c177
<        4: invokespecial #93                 // Method com/squareup/okhttp/Headers$Builder."<init>":()V
---
>        4: invokespecial #27                 // Method com/squareup/okhttp/Headers$Builder."<init>":()V
180c180
<        9: invokestatic  #12                 // Method com/squareup/okhttp/Headers$Builder.access$000:(Lcom/squareup/okhttp/Headers$Builder;)Ljava/util/List;
---
>        9: invokestatic  #3                  // Method com/squareup/okhttp/Headers$Builder.access$000:(Lcom/squareup/okhttp/Headers$Builder;)Ljava/util/List;
182,183c182,183
<       13: getfield      #32                 // Field namesAndValues:[Ljava/lang/String;
<       16: invokestatic  #94                 // Method java/util/Collections.addAll:(Ljava/util/Collection;[Ljava/lang/Object;)Z
---
>       13: getfield      #8                  // Field namesAndValues:[Ljava/lang/String;
>       16: invokestatic  #28                 // Method java/util/Collections.addAll:(Ljava/util/Collection;[Ljava/lang/Object;)Z
190c190
<        0: new           #98                 // class java/lang/StringBuilder
---
>        0: new           #29                 // class java/lang/StringBuilder
192c192
<        4: invokespecial #100                // Method java/lang/StringBuilder."<init>":()V
---
>        4: invokespecial #30                 // Method java/lang/StringBuilder."<init>":()V
197c197
<       11: invokevirtual #57                 // Method size:()I
---
>       11: invokevirtual #15                 // Method size:()I
205,208c205,208
<       23: invokevirtual #58                 // Method name:(I)Ljava/lang/String;
<       26: invokevirtual #101                // Method java/lang/StringBuilder.append:(Ljava/lang/String;)Ljava/lang/StringBuilder;
<       29: ldc           #105                // String :
<       31: invokevirtual #101                // Method java/lang/StringBuilder.append:(Ljava/lang/String;)Ljava/lang/StringBuilder;
---
>       23: invokevirtual #16                 // Method name:(I)Ljava/lang/String;
>       26: invokevirtual #31                 // Method java/lang/StringBuilder.append:(Ljava/lang/String;)Ljava/lang/StringBuilder;
>       29: ldc           #32                 // String :
>       31: invokevirtual #31                 // Method java/lang/StringBuilder.append:(Ljava/lang/String;)Ljava/lang/StringBuilder;
211,214c211,214
<       36: invokevirtual #81                 // Method value:(I)Ljava/lang/String;
<       39: invokevirtual #101                // Method java/lang/StringBuilder.append:(Ljava/lang/String;)Ljava/lang/StringBuilder;
<       42: ldc           #107                // String \n
<       44: invokevirtual #101                // Method java/lang/StringBuilder.append:(Ljava/lang/String;)Ljava/lang/StringBuilder;
---
>       36: invokevirtual #22                 // Method value:(I)Ljava/lang/String;
>       39: invokevirtual #31                 // Method java/lang/StringBuilder.append:(Ljava/lang/String;)Ljava/lang/StringBuilder;
>       42: ldc           #33                 // String \n
>       44: invokevirtual #31                 // Method java/lang/StringBuilder.append:(Ljava/lang/String;)Ljava/lang/StringBuilder;
219c219
<       55: invokevirtual #109                // Method java/lang/StringBuilder.toString:()Ljava/lang/String;
---
>       55: invokevirtual #34                 // Method java/lang/StringBuilder.toString:()Ljava/lang/String;
224c224
<        0: new           #113                // class java/util/LinkedHashMap
---
>        0: new           #35                 // class java/util/LinkedHashMap
226c226
<        4: invokespecial #115                // Method java/util/LinkedHashMap."<init>":()V
---
>        4: invokespecial #36                 // Method java/util/LinkedHashMap."<init>":()V
231c231
<       11: invokevirtual #57                 // Method size:()I
---
>       11: invokevirtual #15                 // Method size:()I
238c238
<       22: invokevirtual #58                 // Method name:(I)Ljava/lang/String;
---
>       22: invokevirtual #16                 // Method name:(I)Ljava/lang/String;
242,243c242,243
<       30: invokeinterface #116,  2          // InterfaceMethod java/util/Map.get:(Ljava/lang/Object;)Ljava/lang/Object;
<       35: checkcast     #19                 // class java/util/List
---
>       30: invokeinterface #37,  2           // InterfaceMethod java/util/Map.get:(Ljava/lang/Object;)Ljava/lang/Object;
>       35: checkcast     #38                 // class java/util/List
247c247
<       45: new           #76                 // class java/util/ArrayList
---
>       45: new           #20                 // class java/util/ArrayList
250c250
<       50: invokespecial #78                 // Method java/util/ArrayList."<init>":(I)V
---
>       50: invokespecial #21                 // Method java/util/ArrayList."<init>":(I)V
255c255
<       60: invokeinterface #121,  3          // InterfaceMethod java/util/Map.put:(Ljava/lang/Object;Ljava/lang/Object;)Ljava/lang/Object;
---
>       60: invokeinterface #39,  3           // InterfaceMethod java/util/Map.put:(Ljava/lang/Object;Ljava/lang/Object;)Ljava/lang/Object;
260,261c260,261
<       70: invokevirtual #81                 // Method value:(I)Ljava/lang/String;
<       73: invokeinterface #84,  2           // InterfaceMethod java/util/List.add:(Ljava/lang/Object;)Z
---
>       70: invokevirtual #22                 // Method value:(I)Ljava/lang/String;
>       73: invokeinterface #23,  2           // InterfaceMethod java/util/List.add:(Ljava/lang/Object;)Z
281c281
<       13: invokevirtual #72                 // Method java/lang/String.equalsIgnoreCase:(Ljava/lang/String;)Z
---
>       13: invokevirtual #19                 // Method java/lang/String.equalsIgnoreCase:(Ljava/lang/String;)Z
303c303
<       11: new           #125                // class java/lang/IllegalArgumentException
---
>       11: new           #40                 // class java/lang/IllegalArgumentException
305,306c305,306
<       15: ldc           #127                // String Expected alternating header names and values
<       17: invokespecial #129                // Method java/lang/IllegalArgumentException."<init>":(Ljava/lang/String;)V
---
>       15: ldc           #41                 // String Expected alternating header names and values
>       17: invokespecial #42                 // Method java/lang/IllegalArgumentException."<init>":(Ljava/lang/String;)V
309,310c309,310
<       22: invokevirtual #132                // Method "[Ljava/lang/String;".clone:()Ljava/lang/Object;
<       25: checkcast     #30                 // class "[Ljava/lang/String;"
---
>       22: invokevirtual #43                 // Method "[Ljava/lang/String;".clone:()Ljava/lang/Object;
>       25: checkcast     #7                  // class "[Ljava/lang/String;"
322c322
<       43: new           #125                // class java/lang/IllegalArgumentException
---
>       43: new           #40                 // class java/lang/IllegalArgumentException
324,325c324,325
<       47: ldc           #136                // String Headers cannot be null
<       49: invokespecial #129                // Method java/lang/IllegalArgumentException."<init>":(Ljava/lang/String;)V
---
>       47: ldc           #44                 // String Headers cannot be null
>       49: invokespecial #42                 // Method java/lang/IllegalArgumentException."<init>":(Ljava/lang/String;)V
332c332
<       58: invokevirtual #138                // Method java/lang/String.trim:()Ljava/lang/String;
---
>       58: invokevirtual #45                 // Method java/lang/String.trim:()Ljava/lang/String;
353c353
<       87: invokevirtual #141                // Method java/lang/String.length:()I
---
>       87: invokevirtual #46                 // Method java/lang/String.length:()I
357c357
<       95: invokevirtual #144                // Method java/lang/String.indexOf:(I)I
---
>       95: invokevirtual #47                 // Method java/lang/String.indexOf:(I)I
362c362
<      104: invokevirtual #144                // Method java/lang/String.indexOf:(I)I
---
>      104: invokevirtual #47                 // Method java/lang/String.indexOf:(I)I
365c365
<      111: new           #125                // class java/lang/IllegalArgumentException
---
>      111: new           #40                 // class java/lang/IllegalArgumentException
367c367
<      115: new           #98                 // class java/lang/StringBuilder
---
>      115: new           #29                 // class java/lang/StringBuilder
369,371c369,371
<      119: invokespecial #100                // Method java/lang/StringBuilder."<init>":()V
<      122: ldc           #148                // String Unexpected header:
<      124: invokevirtual #101                // Method java/lang/StringBuilder.append:(Ljava/lang/String;)Ljava/lang/StringBuilder;
---
>      119: invokespecial #30                 // Method java/lang/StringBuilder."<init>":()V
>      122: ldc           #48                 // String Unexpected header:
>      124: invokevirtual #31                 // Method java/lang/StringBuilder.append:(Ljava/lang/String;)Ljava/lang/StringBuilder;
373,375c373,375
<      128: invokevirtual #101                // Method java/lang/StringBuilder.append:(Ljava/lang/String;)Ljava/lang/StringBuilder;
<      131: ldc           #105                // String :
<      133: invokevirtual #101                // Method java/lang/StringBuilder.append:(Ljava/lang/String;)Ljava/lang/StringBuilder;
---
>      128: invokevirtual #31                 // Method java/lang/StringBuilder.append:(Ljava/lang/String;)Ljava/lang/StringBuilder;
>      131: ldc           #32                 // String :
>      133: invokevirtual #31                 // Method java/lang/StringBuilder.append:(Ljava/lang/String;)Ljava/lang/StringBuilder;
377,379c377,379
<      137: invokevirtual #101                // Method java/lang/StringBuilder.append:(Ljava/lang/String;)Ljava/lang/StringBuilder;
<      140: invokevirtual #109                // Method java/lang/StringBuilder.toString:()Ljava/lang/String;
<      143: invokespecial #129                // Method java/lang/IllegalArgumentException."<init>":(Ljava/lang/String;)V
---
>      137: invokevirtual #31                 // Method java/lang/StringBuilder.append:(Ljava/lang/String;)Ljava/lang/StringBuilder;
>      140: invokevirtual #34                 // Method java/lang/StringBuilder.toString:()Ljava/lang/String;
>      143: invokespecial #42                 // Method java/lang/IllegalArgumentException."<init>":(Ljava/lang/String;)V
383c383
<      153: new           #2                  // class com/squareup/okhttp/Headers
---
>      153: new           #49                 // class com/squareup/okhttp/Headers
386c386
<      158: invokespecial #150                // Method "<init>":([Ljava/lang/String;)V
---
>      158: invokespecial #50                 // Method "<init>":([Ljava/lang/String;)V
393c393
<        4: new           #125                // class java/lang/IllegalArgumentException
---
>        4: new           #40                 // class java/lang/IllegalArgumentException
395,396c395,396
<        8: ldc           #153                // String Expected map with header names and values
<       10: invokespecial #129                // Method java/lang/IllegalArgumentException."<init>":(Ljava/lang/String;)V
---
>        8: ldc           #51                 // String Expected map with header names and values
>       10: invokespecial #42                 // Method java/lang/IllegalArgumentException."<init>":(Ljava/lang/String;)V
399c399
<       15: invokeinterface #155,  1          // InterfaceMethod java/util/Map.size:()I
---
>       15: invokeinterface #52,  1           // InterfaceMethod java/util/Map.size:()I
402c402
<       22: anewarray     #24                 // class java/lang/String
---
>       22: anewarray     #5                  // class java/lang/String
407,408c407,408
<       29: invokeinterface #156,  1          // InterfaceMethod java/util/Map.entrySet:()Ljava/util/Set;
<       34: invokeinterface #160,  1          // InterfaceMethod java/util/Set.iterator:()Ljava/util/Iterator;
---
>       29: invokeinterface #53,  1           // InterfaceMethod java/util/Map.entrySet:()Ljava/util/Set;
>       34: invokeinterface #54,  1           // InterfaceMethod java/util/Set.iterator:()Ljava/util/Iterator;
411c411
<       41: invokeinterface #166,  1          // InterfaceMethod java/util/Iterator.hasNext:()Z
---
>       41: invokeinterface #55,  1           // InterfaceMethod java/util/Iterator.hasNext:()Z
414,415c414,415
<       50: invokeinterface #172,  1          // InterfaceMethod java/util/Iterator.next:()Ljava/lang/Object;
<       55: checkcast     #175                // class java/util/Map$Entry
---
>       50: invokeinterface #56,  1           // InterfaceMethod java/util/Iterator.next:()Ljava/lang/Object;
>       55: checkcast     #57                 // class java/util/Map$Entry
418c418
<       62: invokeinterface #177,  1          // InterfaceMethod java/util/Map$Entry.getKey:()Ljava/lang/Object;
---
>       62: invokeinterface #58,  1           // InterfaceMethod java/util/Map$Entry.getKey:()Ljava/lang/Object;
421c421
<       72: invokeinterface #180,  1          // InterfaceMethod java/util/Map$Entry.getValue:()Ljava/lang/Object;
---
>       72: invokeinterface #59,  1           // InterfaceMethod java/util/Map$Entry.getValue:()Ljava/lang/Object;
423c423
<       80: new           #125                // class java/lang/IllegalArgumentException
---
>       80: new           #40                 // class java/lang/IllegalArgumentException
425,426c425,426
<       84: ldc           #136                // String Headers cannot be null
<       86: invokespecial #129                // Method java/lang/IllegalArgumentException."<init>":(Ljava/lang/String;)V
---
>       84: ldc           #44                 // String Headers cannot be null
>       86: invokespecial #42                 // Method java/lang/IllegalArgumentException."<init>":(Ljava/lang/String;)V
429,431c429,431
<       92: invokeinterface #177,  1          // InterfaceMethod java/util/Map$Entry.getKey:()Ljava/lang/Object;
<       97: checkcast     #24                 // class java/lang/String
<      100: invokevirtual #138                // Method java/lang/String.trim:()Ljava/lang/String;
---
>       92: invokeinterface #58,  1           // InterfaceMethod java/util/Map$Entry.getKey:()Ljava/lang/Object;
>       97: checkcast     #5                  // class java/lang/String
>      100: invokevirtual #45                 // Method java/lang/String.trim:()Ljava/lang/String;
434,436c434,436
<      107: invokeinterface #180,  1          // InterfaceMethod java/util/Map$Entry.getValue:()Ljava/lang/Object;
<      112: checkcast     #24                 // class java/lang/String
<      115: invokevirtual #138                // Method java/lang/String.trim:()Ljava/lang/String;
---
>      107: invokeinterface #59,  1           // InterfaceMethod java/util/Map$Entry.getValue:()Ljava/lang/Object;
>      112: checkcast     #5                  // class java/lang/String
>      115: invokevirtual #45                 // Method java/lang/String.trim:()Ljava/lang/String;
439c439
<      122: invokevirtual #141                // Method java/lang/String.length:()I
---
>      122: invokevirtual #46                 // Method java/lang/String.length:()I
443c443
<      131: invokevirtual #144                // Method java/lang/String.indexOf:(I)I
---
>      131: invokevirtual #47                 // Method java/lang/String.indexOf:(I)I
448c448
<      141: invokevirtual #144                // Method java/lang/String.indexOf:(I)I
---
>      141: invokevirtual #47                 // Method java/lang/String.indexOf:(I)I
451c451
<      148: new           #125                // class java/lang/IllegalArgumentException
---
>      148: new           #40                 // class java/lang/IllegalArgumentException
453c453
<      152: new           #98                 // class java/lang/StringBuilder
---
>      152: new           #29                 // class java/lang/StringBuilder
455,457c455,457
<      156: invokespecial #100                // Method java/lang/StringBuilder."<init>":()V
<      159: ldc           #148                // String Unexpected header:
<      161: invokevirtual #101                // Method java/lang/StringBuilder.append:(Ljava/lang/String;)Ljava/lang/StringBuilder;
---
>      156: invokespecial #30                 // Method java/lang/StringBuilder."<init>":()V
>      159: ldc           #48                 // String Unexpected header:
>      161: invokevirtual #31                 // Method java/lang/StringBuilder.append:(Ljava/lang/String;)Ljava/lang/StringBuilder;
459,461c459,461
<      166: invokevirtual #101                // Method java/lang/StringBuilder.append:(Ljava/lang/String;)Ljava/lang/StringBuilder;
<      169: ldc           #105                // String :
<      171: invokevirtual #101                // Method java/lang/StringBuilder.append:(Ljava/lang/String;)Ljava/lang/StringBuilder;
---
>      166: invokevirtual #31                 // Method java/lang/StringBuilder.append:(Ljava/lang/String;)Ljava/lang/StringBuilder;
>      169: ldc           #32                 // String :
>      171: invokevirtual #31                 // Method java/lang/StringBuilder.append:(Ljava/lang/String;)Ljava/lang/StringBuilder;
463,465c463,465
<      176: invokevirtual #101                // Method java/lang/StringBuilder.append:(Ljava/lang/String;)Ljava/lang/StringBuilder;
<      179: invokevirtual #109                // Method java/lang/StringBuilder.toString:()Ljava/lang/String;
<      182: invokespecial #129                // Method java/lang/IllegalArgumentException."<init>":(Ljava/lang/String;)V
---
>      176: invokevirtual #31                 // Method java/lang/StringBuilder.append:(Ljava/lang/String;)Ljava/lang/StringBuilder;
>      179: invokevirtual #34                 // Method java/lang/StringBuilder.toString:()Ljava/lang/String;
>      182: invokespecial #42                 // Method java/lang/IllegalArgumentException."<init>":(Ljava/lang/String;)V
479c479
<      204: new           #2                  // class com/squareup/okhttp/Headers
---
>      204: new           #49                 // class com/squareup/okhttp/Headers
482c482
<      209: invokespecial #150                // Method "<init>":([Ljava/lang/String;)V
---
>      209: invokespecial #50                 // Method "<init>":([Ljava/lang/String;)V
